Metadata-Version: 2.1
Name: aptos-sdk
Version: 0.9.2
Summary: Aptos SDK
Home-page: https://github.com/aptos-labs/aptos-core/tree/main/ecosystem/python/sdk
License: Apache-2.0
Keywords: web3,sdk,aptos,blockchain
Author: Aptos Labs
Author-email: opensource@aptoslabs.com
Requires-Python: >=3.8.1
Classifier: License :: OSI Approved :: Apache Software License
Classifier: Programming Language :: Python :: 3
Classifier: Programming Language :: Python :: 3.9
Classifier: Programming Language :: Python :: 3.10
Classifier: Programming Language :: Python :: 3.11
Classifier: Programming Language :: Python :: 3.12
Requires-Dist: PyNaCl (>=1.5.0,<2.0.0)
Requires-Dist: behave (>=1.2.6,<2.0.0)
Requires-Dist: ecdsa (==0.18.0)
Requires-Dist: httpx (>=0.27.0,<0.28.0)
Requires-Dist: python-graphql-client (>=0.4.3,<0.5.0)
Requires-Dist: tomli (>=2.0.1,<3.0.0)
Requires-Dist: types-six (>=1.16.21.20240513,<2.0.0.0)
Requires-Dist: typing-extensions (>=4.4.0,<5.0.0)
Project-URL: Repository, https://github.com/aptos-labs/aptos-core
